MANIFEST.in
README.md
setup.py
elle/units/__init__.py
elle/units/postprocessing.py
elle/units/simple.py
elle/units/types.py
elle/units/units.py
elle/units/utils.py
elle/units/build/english-w_abbrev.json
elle/units/build/english_engineering-w_abbrev.json
elle/units/build/kip_in_F-w_abbrev.json
elle/units/build/metric-w_abbrev.json
elle/units/build/si-w_abbrev.json
elle/units/build/units.json
elle_units.egg-info/PKG-INFO
elle_units.egg-info/SOURCES.txt
elle_units.egg-info/dependency_links.txt
elle_units.egg-info/namespace_packages.txt
elle_units.egg-info/top_level.txt