Metadata-Version: 1.1
Name: elle-units
Version: 0.0.3
Summary: Utilities for managing units in calculations
Home-page: https://github.com/claudioperez/elle-units
Author: Claudio Perez
Author-email: claudio_perez@berkeley.edu
License: UNKNOWN
Platform: UNKNOWN
Classifier: Development Status :: 2 - Pre-Alpha
Classifier: Programming Language :: Python :: 3
